[
  {
    "name": "Hi Beauty",
    "description": "Ofrece cajas de suscripción y una variedad de productos de belleza. Ofrece cajas de suscripción y una variedad de productos de belleza. Ofrece cajas de suscripción y una variedad de productos de belleza.",
    "featured": true,
    "type": "website",
    "link": "https://hibeauty.com.co/",
    "technologies": [
      {
        "id": "react.js",
        "name": "React.js"
      },
      {
        "id": "next.js",
        "name": "Next.js"
      },
      {
        "id": "tailwindcss",
        "name": "Tailwind CSS"
      }
    ]
  }
]
